Metadata-Version: 1.0
Name: distribution-pack
Version: 0.3
Summary: Gaussian and Binomial distributions
Home-page: UNKNOWN
Author: Igor Santos
Author-email: ssantos.igor@hotmail.com
License: UNKNOWN
Platform: UNKNOWN
